compactletterdisplay/__init__.py
compactletterdisplay/anova.py
compactletterdisplay/cld_calculator.py
compactletterdisplay/pairwise_comp.py
compactletterdisplay-0.11.dist-info/LICENSE
compactletterdisplay-0.11.dist-info/METADATA
compactletterdisplay-0.11.dist-info/WHEEL
compactletterdisplay-0.11.dist-info/top_level.txt
compactletterdisplay-0.11.dist-info/RECORD
