Metadata-Version: 2.1
Name: compactletterdisplay
Version: 0.11
Summary: A compact letter display implementation in Python, which summarizes results of posthoc comparisons.
Home-page: https://github.com/sujeet-bhalerao/compact-letter-display
Author: Sujeet Bhalerao
Author-email: sujeetbhalerao@gmail.com
Classifier: Development Status :: 3 - Alpha
Classifier: Intended Audience :: Science/Research
Classifier: License :: OSI Approved :: GNU Affero General Public License v3 or later (AGPLv3+)
Classifier: Programming Language :: Python :: 3
Classifier: Programming Language :: Python :: 3.7
Classifier: Programming Language :: Python :: 3.8
Classifier: Programming Language :: Python :: 3.9
Classifier: Programming Language :: Python :: 3.10
Classifier: Topic :: Scientific/Engineering
Classifier: Topic :: Software Development :: Libraries
Classifier: Topic :: Software Development :: Libraries :: Python Modules
License-File: LICENSE
Requires-Dist: pandas
Requires-Dist: scipy
Requires-Dist: statsmodels
